<annotation>
	<folder>Images</folder>
	<filename>Images.9678c124-b91d-11ed-8af6-b42e99eb25df.jpg</filename>
	<path>C:\Users\Wacha\Desktop\OD\Tensorflow\workspace\images\collectedimages\Images\Images.9678c124-b91d-11ed-8af6-b42e99eb25df.jpg</path>
	<source>
		<database>Unknown</database>
	</source>
	<size>
		<width>640</width>
		<height>480</height>
		<depth>3</depth>
	</size>
	<segmented>0</segmented>
	<object>
		<name>W-Knight</name>
		<pose>Unspecified</pose>
		<truncated>0</truncated>
		<difficult>0</difficult>
		<bndbox>
			<xmin>182</xmin>
			<ymin>44</ymin>
			<xmax>214</xmax>
			<ymax>109</ymax>
		</bndbox>
	</object>
	<object>
		<name>W-Bishop</name>
		<pose>Unspecified</pose>
		<truncated>0</truncated>
		<difficult>0</difficult>
		<bndbox>
			<xmin>114</xmin>
			<ymin>299</ymin>
			<xmax>174</xmax>
			<ymax>362</ymax>
		</bndbox>
	</object>
	<object>
		<name>B-Bishop</name>
		<pose>Unspecified</pose>
		<truncated>0</truncated>
		<difficult>0</difficult>
		<bndbox>
			<xmin>438</xmin>
			<ymin>43</ymin>
			<xmax>475</xmax>
			<ymax>110</ymax>
		</bndbox>
	</object>
	<object>
		<name>B-Knight</name>
		<pose>Unspecified</pose>
		<truncated>0</truncated>
		<difficult>0</difficult>
		<bndbox>
			<xmin>505</xmin>
			<ymin>306</ymin>
			<xmax>572</xmax>
			<ymax>373</ymax>
		</bndbox>
	</object>
</annotation>
